OpenSolve/Client.py
opensolve-0.0.4.dist-info/METADATA
opensolve-0.0.4.dist-info/WHEEL
opensolve-0.0.4.dist-info/licenses/LICENSE
opensolve-0.0.4.dist-info/RECORD
