Metadata-Version: 2.3
Name: OpenSolve
Version: 0.0.4
Summary: The Python client for the OpenSolve linear optimization solver service.
Project-URL: Homepage, https://open-solve.com
Project-URL: Issues, https://github.com/greg-open-solve/OpenSolveClient
Author-email: Greg Hauser <greg@open-solve.com>
License-File: LICENSE
Classifier: License :: OSI Approved :: MIT License
Classifier: Operating System :: OS Independent
Classifier: Programming Language :: Python :: 3
Requires-Python: >=3.11
Requires-Dist: requests
